passhfiles/__init__.py
passhfiles/__pkginfo__.py
passhfiles/dialogs/AboutDialog.py
passhfiles/dialogs/FileEditorDialog.py
passhfiles/dialogs/SessionDialog.py
passhfiles/icons/about.png
passhfiles/icons/directory.png
passhfiles/icons/exit.png
passhfiles/icons/file.png
passhfiles/icons/key.png
passhfiles/icons/new_session.png
passhfiles/icons/passhfiles.png
passhfiles/icons/preferences.png
passhfiles/icons/server.png
passhfiles/icons/session.png
passhfiles/icons/trash.png
passhfiles/kernel/KeyStore.py
passhfiles/kernel/Singleton.py
passhfiles/kernel/__init__.py
passhfiles/models/IFileSystemModel.py
passhfiles/models/LocalFileSystemModel.py
passhfiles/models/RemoteFileSystemModel.py
passhfiles/models/SessionsModel.py
passhfiles/models/__init__.py
passhfiles/utils/Gui.py
passhfiles/utils/Numbers.py
passhfiles/utils/Platform.py
passhfiles/utils/ProgressBar.py
passhfiles/utils/Security.py
passhfiles/utils/String.py
passhfiles/utils/__init__.py
passhfiles/views/FileSystemTableView.py
passhfiles/views/MainWindow.py
passhfiles/views/SessionsTreeView.py
passhfiles/views/__init__.py
passhfiles/widgets/LoggerWidget.py
passhfiles/widgets/__init__.py
passhfiles-1.0.3.data/scripts/passhfiles
passhfiles-1.0.3.dist-info/LICENSE
passhfiles-1.0.3.dist-info/METADATA
passhfiles-1.0.3.dist-info/WHEEL
passhfiles-1.0.3.dist-info/top_level.txt
passhfiles-1.0.3.dist-info/RECORD
